main.py
lightseqe-98.7.dist-info/METADATA
lightseqe-98.7.dist-info/WHEEL
lightseqe-98.7.dist-info/top_level.txt
lightseqe-98.7.dist-info/RECORD
